llama_index/readers/microsoft_sharepoint/__init__.py
llama_index/readers/microsoft_sharepoint/base.py
llama_index/readers/microsoft_sharepoint/file_path_info.png
llama_index_readers_microsoft_sharepoint-0.6.1.dist-info/METADATA
llama_index_readers_microsoft_sharepoint-0.6.1.dist-info/WHEEL
llama_index_readers_microsoft_sharepoint-0.6.1.dist-info/licenses/LICENSE
llama_index_readers_microsoft_sharepoint-0.6.1.dist-info/RECORD
