Metadata-Version: 2.4
Name: llama-index-readers-microsoft-sharepoint
Version: 0.6.1
Summary: llama-index readers microsoft_sharepoint integration
Author-email: Your Name <you@example.com>
Maintainer: arun-soliton
License-Expression: MIT
License-File: LICENSE
Keywords: microsoft 365,microsoft365,sharepoint
Requires-Python: <4.0,>=3.9
Requires-Dist: llama-index-core<0.15,>=0.13.0
Requires-Dist: llama-index-readers-file<0.6,>=0.5.0
Requires-Dist: requests<3,>=2.31.0
